sphinx_subprojecttoctree-0.6.0.dist-info/licenses/LICENSE
subprojecttoctree/__init__.py
subprojecttoctree/__version__.py
subprojecttoctree/builders.py
subprojecttoctree/toctree.py
subprojecttoctree/utils.py
sphinx_subprojecttoctree-0.6.0.dist-info/METADATA
sphinx_subprojecttoctree-0.6.0.dist-info/WHEEL
sphinx_subprojecttoctree-0.6.0.dist-info/top_level.txt
sphinx_subprojecttoctree-0.6.0.dist-info/RECORD
