Metadata-Version: 2.4
Name: sphinx-subprojecttoctree
Version: 0.6.0
Summary: Subprojecttoctrees is a Sphinx extension that aims to facilitate the integration of several documentation sources into a single Read the Docs webpage.
Home-page: https://sphinx-subprojecttoctree.readthedocs.io
Author: Dries Schaumont
Author-email: dries.schaumont@ilvo.vlaanderen.be
License: MIT
Project-URL: Changelog, https://sphinx-subprojecttoctree.readthedocs.io/en/latest/changelog.html
Classifier: Operating System :: OS Independent
Classifier: Framework :: Sphinx :: Extension
Classifier: Development Status :: 4 - Beta
Classifier: License :: OSI Approved :: MIT License
Classifier: Programming Language :: Python :: 3 :: Only
Classifier: Topic :: Documentation :: Sphinx
Requires-Python: >=3.10
License-File: LICENSE
Requires-Dist: sphinx<9,>=7.0.0
Requires-Dist: requests~=2.32.5
Provides-Extra: docs
Requires-Dist: sphinx_rtd_theme<4.0.0,>=2.0.0; extra == "docs"
Requires-Dist: sphinx-issues~=5.0.0; extra == "docs"
Provides-Extra: dev
Requires-Dist: tox; extra == "dev"
Requires-Dist: pre-commit; extra == "dev"
Dynamic: license-file
